hellonbdev/__init__.py
hellonbdev/_nbdev.py
hellonbdev/core.py
nbdev_tutorial/__init__.py
nbdev_tutorial/_nbdev.py
nbdev_tutorial/core.py
nbdev_tutorial-0.0.4.dist-info/LICENSE
nbdev_tutorial-0.0.4.dist-info/METADATA
nbdev_tutorial-0.0.4.dist-info/WHEEL
nbdev_tutorial-0.0.4.dist-info/entry_points.txt
nbdev_tutorial-0.0.4.dist-info/top_level.txt
nbdev_tutorial-0.0.4.dist-info/RECORD
